document_processing/__init__.py
document_processing-1.0.1.202208310820.dist-info/AUTHORS
document_processing-1.0.1.202208310820.dist-info/LICENSE
document_processing-1.0.1.202208310820.dist-info/METADATA
document_processing-1.0.1.202208310820.dist-info/WHEEL
document_processing-1.0.1.202208310820.dist-info/top_level.txt
document_processing-1.0.1.202208310820.dist-info/RECORD
