Metadata-Version: 2.1
Name: document-processing
Version: 1.0.1.202208310820
Summary: Pre-process documents for Natural Language Processing using spaCy models
Home-page: https://gitlab.univ-lr.fr/cross-lingual-event-tracking/developpement/from-documents-to-events/document_processing
Author: Guillaume Bernard
Author-email: contact@guillaume-bernard.fr
License: GPLv3
Project-URL: Bug Tracker, https://gitlab.univ-lr.fr/cross-lingual-event-tracking/developpement/from-documents-to-events/document_processing/-/issues
Platform: UNKNOWN
Classifier: Programming Language :: Python :: 3.9
Classifier: License :: OSI Approved :: GNU General Public License v3 (GPLv3)
Classifier: Operating System :: POSIX :: Linux
Classifier: Topic :: Scientific/Engineering :: Artificial Intelligence
Classifier: Intended Audience :: Science/Research
Requires-Python: >=3.9
License-File: LICENSE
License-File: AUTHORS
Requires-Dist: pandas (~=1.3.5)
Requires-Dist: setuptools (~=53.0.0)
Requires-Dist: spacy (~=3.2.1)
